LICENSE
MANIFEST.in
README
README.md
setup.cfg
setup.py
pyiArduinoI2Cbumper/__init__.py
pyiArduinoI2Cbumper/additional_defines.h
pyiArduinoI2Cbumper/iarduino_I2C_Bumper.cpp
pyiArduinoI2Cbumper/iarduino_I2C_Bumper.h
pyiArduinoI2Cbumper/iarduino_I2C_Bumper.pxd
pyiArduinoI2Cbumper/iarduino_I2C_PI.cpp
pyiArduinoI2Cbumper/iarduino_I2C_PI.h
pyiArduinoI2Cbumper/pyiArduinoI2Cbumper.cpp
pyiArduinoI2Cbumper/pyiArduinoI2Cbumper.pyx
pyiArduinoI2Cbumper/setup.py
pyiArduinoI2Cbumper.egg-info/PKG-INFO
pyiArduinoI2Cbumper.egg-info/SOURCES.txt
pyiArduinoI2Cbumper.egg-info/dependency_links.txt
pyiArduinoI2Cbumper.egg-info/top_level.txt
pyiArduinoI2Cbumper/cpp/FindDevices.cpp
pyiArduinoI2Cbumper/cpp/NewAddress.cpp
pyiArduinoI2Cbumper/cpp/Serial.h
pyiArduinoI2Cbumper/cpp/changeLineType.cpp
pyiArduinoI2Cbumper/cpp/changeLineTypeAuto.cpp
pyiArduinoI2Cbumper/cpp/controlCalibrationButton.cpp
pyiArduinoI2Cbumper/cpp/getLineAnalog.cpp
pyiArduinoI2Cbumper/cpp/getLineDigital.cpp
pyiArduinoI2Cbumper/cpp/getLineDigitalFast.cpp
pyiArduinoI2Cbumper/cpp/setCalibrationAuto.cpp
pyiArduinoI2Cbumper/cpp/setCalibrationManual.cpp
pyiArduinoI2Cbumper/cpp/setTurnSignal.cpp
pyiArduinoI2Cbumper/cpp/setTurnSignalAuto.cpp
pyiArduinoI2Cbumper/examples/FindDevices.py
pyiArduinoI2Cbumper/examples/changeLineType.py
pyiArduinoI2Cbumper/examples/changeLineTypeAuto.py
pyiArduinoI2Cbumper/examples/controlCalibrationButton.py
pyiArduinoI2Cbumper/examples/getLineAnalog.py
pyiArduinoI2Cbumper/examples/getLineDigital.py
pyiArduinoI2Cbumper/examples/getLineDigitalFast.py
pyiArduinoI2Cbumper/examples/newAddress.py
pyiArduinoI2Cbumper/examples/setCalibrationAuto.py
pyiArduinoI2Cbumper/examples/setCalibrationManual.py
pyiArduinoI2Cbumper/examples/setTurnSignal.py
pyiArduinoI2Cbumper/examples/setTurnSignalAuto.py